reflex_plot/__init__.py
reflex_plot/core.py
reflex_plot-0.1.0.dist-info/METADATA
reflex_plot-0.1.0.dist-info/WHEEL
reflex_plot-0.1.0.dist-info/entry_points.txt
reflex_plot-0.1.0.dist-info/licenses/LICENSE
reflex_plot-0.1.0.dist-info/RECORD
