Metadata-Version: 2.3
Name: reflex-plot
Version: 0.1.0
Summary: Plot your dataframe with reflex!
Project-URL: source, https://github.com/lucianosrp/reflex-plot
Author-email: Luciano Scarpulla <66913960+lucianosrp@users.noreply.github.com>
License-File: LICENSE
Keywords: dashboard,pandas,plotting,reflex,reflex-plot
Classifier: License :: OSI Approved :: MIT License
Classifier: Operating System :: OS Independent
Classifier: Programming Language :: Python :: 3
Requires-Python: >=3.9
Requires-Dist: pandas>=2.0.0
Requires-Dist: reflex>=0.5.9
